<?xml version="1.0" encoding="UTF-8"?>
<Tokens version="1.0">
	<File path="Classes/WBBaseMediaObject.html">
		
		<Token>
			<TokenIdentifier>//apple_ref/occ/cl/WBBaseMediaObject</TokenIdentifier>
			<Abstract type="html">消息中包含的多媒体数据对象基类</Abstract>
			<DeclaredIn>WeiboSDK.h</DeclaredIn>
			
			<NodeRef refid="431"/>
		</Token>
		
		
		<Token>
			<TokenIdentifier>//apple_ref/occ/instm/WBBaseMediaObject/setObjectID:</TokenIdentifier>
			<Abstract type="html">对象唯一ID，用于唯一标识一个多媒体内容</Abstract>
			<DeclaredIn>WeiboSDK.h</DeclaredIn>			
			
			<Declaration>@property (nonatomic, retain) NSString *objectID</Declaration>
			
			
			<Anchor>//api/name/objectID</Anchor>
		</Token>
		
		<Token>
			<TokenIdentifier>//apple_ref/occ/instp/WBBaseMediaObject/objectID</TokenIdentifier>
			<Abstract type="html">对象唯一ID，用于唯一标识一个多媒体内容</Abstract>
			<DeclaredIn>WeiboSDK.h</DeclaredIn>			
			
			<Declaration>@property (nonatomic, retain) NSString *objectID</Declaration>
			
			
			<Anchor>//api/name/objectID</Anchor>
		</Token>
		
		<Token>
			<TokenIdentifier>//apple_ref/occ/instm/WBBaseMediaObject/setTitle:</TokenIdentifier>
			<Abstract type="html">多媒体内容标题</Abstract>
			<DeclaredIn>WeiboSDK.h</DeclaredIn>			
			
			<Declaration>@property (nonatomic, retain) NSString *title</Declaration>
			
			
			<Anchor>//api/name/title</Anchor>
		</Token>
		
		<Token>
			<TokenIdentifier>//apple_ref/occ/instp/WBBaseMediaObject/title</TokenIdentifier>
			<Abstract type="html">多媒体内容标题</Abstract>
			<DeclaredIn>WeiboSDK.h</DeclaredIn>			
			
			<Declaration>@property (nonatomic, retain) NSString *title</Declaration>
			
			
			<Anchor>//api/name/title</Anchor>
		</Token>
		
		<Token>
			<TokenIdentifier>//apple_ref/occ/instm/WBBaseMediaObject/setDescription:</TokenIdentifier>
			<Abstract type="html">多媒体内容描述</Abstract>
			<DeclaredIn>WeiboSDK.h</DeclaredIn>			
			
			<Declaration>@property (nonatomic, retain) NSString *description</Declaration>
			
			
			<Anchor>//api/name/description</Anchor>
		</Token>
		
		<Token>
			<TokenIdentifier>//apple_ref/occ/instp/WBBaseMediaObject/description</TokenIdentifier>
			<Abstract type="html">多媒体内容描述</Abstract>
			<DeclaredIn>WeiboSDK.h</DeclaredIn>			
			
			<Declaration>@property (nonatomic, retain) NSString *description</Declaration>
			
			
			<Anchor>//api/name/description</Anchor>
		</Token>
		
		<Token>
			<TokenIdentifier>//apple_ref/occ/instm/WBBaseMediaObject/setThumbnailData:</TokenIdentifier>
			<Abstract type="html">多媒体内容缩略图</Abstract>
			<DeclaredIn>WeiboSDK.h</DeclaredIn>			
			
			<Declaration>@property (nonatomic, retain) NSData *thumbnailData</Declaration>
			
			
			<Anchor>//api/name/thumbnailData</Anchor>
		</Token>
		
		<Token>
			<TokenIdentifier>//apple_ref/occ/instp/WBBaseMediaObject/thumbnailData</TokenIdentifier>
			<Abstract type="html">多媒体内容缩略图</Abstract>
			<DeclaredIn>WeiboSDK.h</DeclaredIn>			
			
			<Declaration>@property (nonatomic, retain) NSData *thumbnailData</Declaration>
			
			
			<Anchor>//api/name/thumbnailData</Anchor>
		</Token>
		
		<Token>
			<TokenIdentifier>//apple_ref/occ/instm/WBBaseMediaObject/setScheme:</TokenIdentifier>
			<Abstract type="html">点击多媒体内容之后呼起第三方应用特定页面的scheme</Abstract>
			<DeclaredIn>WeiboSDK.h</DeclaredIn>			
			
			<Declaration>@property (nonatomic, retain) NSString *scheme</Declaration>
			
			
			<Anchor>//api/name/scheme</Anchor>
		</Token>
		
		<Token>
			<TokenIdentifier>//apple_ref/occ/instp/WBBaseMediaObject/scheme</TokenIdentifier>
			<Abstract type="html">点击多媒体内容之后呼起第三方应用特定页面的scheme</Abstract>
			<DeclaredIn>WeiboSDK.h</DeclaredIn>			
			
			<Declaration>@property (nonatomic, retain) NSString *scheme</Declaration>
			
			
			<Anchor>//api/name/scheme</Anchor>
		</Token>
		
		<Token>
			<TokenIdentifier>//apple_ref/occ/clm/WBBaseMediaObject/object</TokenIdentifier>
			<Abstract type="html">返回一个 WBBaseMediaObject 对象</Abstract>
			<DeclaredIn>WeiboSDK.h</DeclaredIn>			
			
			<Declaration>+ (id)object</Declaration>
			
			<ReturnValue><Abstract type="html">返回一个自动释放的WBBaseMediaObject对象</Abstract></ReturnValue>
			<Anchor>//api/name/object</Anchor>
		</Token>
		
	</File>
</Tokens>